ff_top.sv

module ff_top(
    input logic clk,
    input logic s,
    input logic reset,
    output logic q,
    output logic q_bar
);

always_ff @(posedge clk) begin
    if (reset)
        q <= 1'b0;
    else
        q <= s;
    q_bar <= ~q;
end

endmodule

Ram.sv
// 

module Ram #(
    parameter ADDRESS_WIDTH = 20,
            DATA_WIDTH = 15
)(
    input logic clk,
    input logic WRITE_EN,
    input logic READ_EN,
    input logic [ADDRESS_WIDTH-1:0] rd_addr,
    input logic [ADDRESS_WIDTH-1:0] wr_addr,
    input logic [DATA_WIDTH-1:0] din,
    output logic [DATA_WIDTH-1:0] RGB
);

logic [DATA_WIDTH-1:0] ram_array [2**ADDRESS_WIDTH-1:0];

always_ff @(posedge clk) begin
    if (WRITE_EN ==1'b1)
        ram_array[wr_addr] <=din;
    if (READ_EN == 1'b1)
        RGB <= ram_array[rd_addr];
end 

endmodule

Counter.sv
// Pointer moves through whole image from top left to bottom right in a rastern pattern and stops at each pixel
// and counts the number of iterations it takes for that specific 'pixel' to diverge. It diverges when the absolute
// value of Z_n is greater than 2. The pixels are assigned a color based on how quickly they diverge. It is assigned
// black if it is in the Mandelbrot set, and therefore never diverges, and red if it diverges. Any color between is purely
// for aesthetic appeal and represents how quickly that point diverges. A true Mandelbrot set is black and white.



module Counter (
  input logic clk,       // Clock input
  input logic rst,       // Reset input (assume active high for this example)
  input logic en,        // Enable input
  output logic [14:0] counter,  // 15-bit counter output
  output logic ovf    // Overflow output
);

  // 15-bit counter register
  logic [14:0] counter_reg;

  always_ff @(posedge clk or posedge rst) begin
    if (rst) begin
      // Reset the counter and overflow signal
      counter_reg <= 15'd0;
      ovf <= 1'b0;
    end else if (en) begin
      if (counter_reg == 15'h7FFF) begin
        // If counter is at maximum value, set overflow and reset counter
        counter_reg <= 15'd0;
        ovf <= 1'b1;
      end else begin
        // Increment counter and clear overflow
        counter_reg <= counter_reg + 15'd1;
        ovf <= 1'b0;
      end
    end
    counter <= counter_reg;
  end


endmodule

Addr_counter.sv
module Addr_counter(
    input logic clk, 
    input logic en, 
    input logic rst, 
    output logic [19:0] addr_count,
    output logic [9:0] X,
    output logic [9:0] Y
);

always_ff @(posedge clk)
begin
    if (rst)
        addr_count <= 20'b0;
    else if (addr_count == 20'hFFFFF)
        addr_count <= 20'b0;
    else if (en)
        addr_count <= addr_count + 20'b01;
        X <= {addr_count[9:0]};
        Y <= {addr_count[19:10]};
end

endmodule

multiplier.sv
// This module multiplies 2 32 bit numbers and truncates the result to produce a 32 bit output.

module multiplier #(
    parameter WIDTH = 32
)(
    input  logic [WIDTH-1:0] a,   // assuming form S,BBBBBBBBBB.DDDDDDDDDDDDDDDDDDDDD (1 sign, 10 bits of data, and 21 decimals)
    input  logic [WIDTH-1:0] b,
    output logic [WIDTH-1:0] result
);

logic [2*WIDTH-1:0] intermediate;

assign intermediate = a*b;
assign result = intermediate[52:21];

endmodule

generator.sv
// This module generates the necessary numbers that provide all the information about a Mandelbrot set.

module generator(
    input logic [31:0] a,
    input logic [31:0] b,
    output logic [31:0] aa_minus_bb,
    output logic [31:0] two_ab,
    output logic [31:0] aa_plus_bb
);

logic [31:0] aa;
logic [31:0] bb;
logic [31:0] ab;

multiplier a_a(
    .a(a),
    .b(a),
    .result(aa)
);

multiplier b_b(
    .a(b),
    .b(b),
    .result(bb)
);

multiplier a_b(
    .a(a),
    .b(b),
    .result(ab)
);

logic [30:0] ab_truncated;
always_comb begin
    aa_minus_bb = aa - bb;
    aa_plus_bb = aa + bb;
    ab_truncated = ab[30:0];
    two_ab = {ab_truncated, 1'b0};
end


endmodule

diverge.sv
module diverge(
    input logic [31:0] a,
    input logc [31:0] b,
    input logic ld,
    input logic clk,
    output logic diverged
);

logic [31:0] A;
logic [31:0] B;
logic [31:0] aaplusbb;
logic [31:0] aaminusbb;
logic [31:0] twoab;

generator GENERATOR(
    .a(A),
    .b(B),
    .aa_minus_bb(aaminusbb),
    .two_ab(twoab),
    .aa_plus_bb(aaplusbb)
);

logic [31:0] s1;
logic [31:0] s2;

logic [31:0] muxout1;
logic [31:0] muxout2;

always_comb begin
    s1 = a + aaminusbb;
    s2 = twoab + b;
    if (a > 8'h00800000) 
        diverged = 1;
    else 
        diverged = 0;  
    muxout1 = ld? 32'b0 : s1;
    muxout2 = ld? 32'b0 : s2;

end

always_ff @(posedge clk) begin
    
end

endmodule

dimensions.sv
// Performs raster pattern
// Overflow is only high when it is finished generating the image

module dimensions(
    input logic clk, 
    input logic en, 
    input logic rst,
    output logic OVF,
    output logic [9:0] X,
    output logic [9:0] Y
);

always_ff @(posedge clk)
    if (rst) begin
        X <= 10'b0;
        Y <= 10'b0;
        OVF <= 1'b0;
    end else if (en) begin
        if (X == 10'h3FF) begin        //3FF = 1023
            if (Y == 10'h2FF) begin    //2FF = 767
                OVF <= 1;
                Y <= 10'b0;
            end

            Y <= Y + 10'b01;
            X <= 10'b0;
        end
        else X <= X + 10'b01;
    end

endmodule

mapper.sv
// This module maps the pixel coordinates (X and Y) onto the complex plane displaying the Mandelbrot visualisation.

module mapper(
    input logic clock,
    input logic rst,
    input logic en,
    input logic [31:0] delta_x,
    input logic [31:0] delta_y,
    input logic [31:0] re_axis_width,
    input logic [31:0] im_axis_width,
    output logic [31:0] real_s,
    output logic [31:0] ims,
    output logic        ovf,
    output logic [9:0] x,
    output logic [9:0] y
);

logic [9:0]  X;
logic [9:0]  Y;
logic [31:0] XtimesDelta;
logic [31:0] YtimesDelta;

dimensions DIMENSIONS(
    .clk(clock),
    .en(en),
    .rst(rst),
    .OVF(ovf),
    .X(X),
    .Y(Y)
);

multiplier XtimesDELTA(
    .a({1'b0, X, 21'b0}),
    .b(delta_x),
    .result(XtimesDelta)
);

multiplier YtimesDELTA(
    .a({1'b0, Y, 21'b0}),
    .b(delta_y),
    .result(YtimesDelta)
);

always_comb begin
    x = {1'b0, X, 21'b0};
    y = {1'b0, Y, 21'b0};
    real_s = XtimesDelta + re_axis_width;
    ims = YtimesDelta + im_axis_width;
end

endmodule

mandelbrot_toplevel.sv
module mandelbrot_toplevel(
    input logic rst,
    input logic clk,
    input logic enable,
    input logic [9:0] x_size,
    input logic [9:0] y_size,
    input logic [31:0] Re_axis_width,
    input logic [31:0] Im_axis_width,
    output logic [14:0] RGB_out, 
    output logic [9:0] X,
    output logic [9:0] Y
);


//mapper wires
logic [31:0] Delta_x = Re_axis_width/{22'b0, x_size};
logic [31:0] Delta_y = Im_axis_width/{22'b0, y_size};
logic [9:0] x_internal;  // real coordinate
logic [9:0] y_internal;  // imag coordinate
logic ovf;  //overflow due to finish image generation 

logic [31:0] real_internal;
logic [31:0] im_internal;

logic q;   //top flipflop output 
logic q_bar;    //~q
logic [14:0] counter_out ;  //out of the bottom counter
logic ovf_it; //overflow for iteration stop (size larger then 2) 

logic or_out;   //output of the or gate
logic div;  //diverged output 

mapper Mapper (
    .clock(clk),
    .rst(rst),
    .en(enable & q_bar & or_out),  //later
    .delta_x(Delta_x),
    .delta_y(Delta_y),
    .re_axis_width(Re_axis_width),
    .im_axis_width(Im_axis_width),
    .real_s(real_internal),
    .ims(im_internal),
    .ovf(ovf),
    .x(x_internal),
    .y(y_internal)
);

diverge DIVERGE(
    .a(real_internal),
    .b(im_internal),
    .ld(or_out),
    .clk(clk),
    .diverged(div)
);

logic [19:0] rd_addr;
Addr_counter addr_counter(
    .clk(clk),
    .rst(rst),
    .en(ovf),
    .addr_count(rd_addr),
    .X(X),
    .Y(Y)
);

Counter counter_mod(
    .clk(clk),
    .rst(or_out),
    .en(enable),
    .counter(counter_out),
    .ovf(ovf_it)
);

Ram ram(
    .clk(clk),
    .WRITE_EN(~ovf),
    .READ_EN(ovf),
    .rd_addr(rd_addr),
    .wr_addr({y_internal,x_internal}),
    .din(counter_out),  // count_out
    .RGB(RGB_out)
);

ff_top top_f(
    .clk(clk),
    .s(ovf),
    .reset(rst),
    .q(q),
    .q_bar(q_bar)
);


always_comb begin
    or_out = div || ovf_it;
end



endmodule

top_test.vcd
$version Generated by VerilatedVcd $end
$date Sat May 25 12:12:54 2024 $end
$timescale 1ps $end

 $scope module TOP $end
  $var wire 32 L Im_axis_width [31:0] $end
  $var wire 15 M RGB_out [14:0] $end
  $var wire 32 K Re_axis_width [31:0] $end
  $var wire 10 N X [9:0] $end
  $var wire 10 O Y [9:0] $end
  $var wire  1 G clk $end
  $var wire  1 H enable $end
  $var wire  1 F rst $end
  $var wire 10 I x_size [9:0] $end
  $var wire 10 J y_size [9:0] $end
  $scope module mandelbrot_toplevel $end
   $var wire 32 P Delta_x [31:0] $end
   $var wire 32 Q Delta_y [31:0] $end
   $var wire 32 L Im_axis_width [31:0] $end
   $var wire 15 M RGB_out [14:0] $end
   $var wire 32 K Re_axis_width [31:0] $end
   $var wire 10 N X [9:0] $end
   $var wire 10 O Y [9:0] $end
   $var wire  1 G clk $end
   $var wire 15 ' counter_out [14:0] $end
   $var wire  1 A div $end
   $var wire  1 H enable $end
   $var wire 32 R im_internal [31:0] $end
   $var wire  1 @ or_out $end
   $var wire  1 $ ovf $end
   $var wire  1 ( ovf_it $end
   $var wire  1 % q $end
   $var wire  1 & q_bar $end
   $var wire 20 ) rd_addr [19:0] $end
   $var wire 32 ? real_internal [31:0] $end
   $var wire  1 F rst $end
   $var wire 10 # x_internal [9:0] $end
   $var wire 10 I x_size [9:0] $end
   $var wire 10 # y_internal [9:0] $end
   $var wire 10 J y_size [9:0] $end
   $scope module DIVERGE $end
    $var wire 32 * A [31:0] $end
    $var wire 32 + B [31:0] $end
    $var wire 32 ? a [31:0] $end
    $var wire 32 - aaminusbb [31:0] $end
    $var wire 32 , aaplusbb [31:0] $end
    $var wire 32 R b [31:0] $end
    $var wire  1 G clk $end
    $var wire  1 A diverged $end
    $var wire  1 @ ld $end
    $var wire 32 D muxout1 [31:0] $end
    $var wire 32 E muxout2 [31:0] $end
    $var wire 32 B s1 [31:0] $end
    $var wire 32 C s2 [31:0] $end
    $var wire 32 . twoab [31:0] $end
    $scope module GENERATOR $end
     $var wire 32 * a [31:0] $end
     $var wire 32 / aa [31:0] $end
     $var wire 32 - aa_minus_bb [31:0] $end
     $var wire 32 , aa_plus_bb [31:0] $end
     $var wire 32 1 ab [31:0] $end
     $var wire 31 2 ab_truncated [30:0] $end
     $var wire 32 + b [31:0] $end
     $var wire 32 0 bb [31:0] $end
     $var wire 32 . two_ab [31:0] $end
     $scope module a_a $end
      $var wire 32 Z WIDTH [31:0] $end
      $var wire 32 * a [31:0] $end
      $var wire 32 * b [31:0] $end
      $var wire 64 3 intermediate [63:0] $end
      $var wire 32 / result [31:0] $end
     $upscope $end
     $scope module a_b $end
      $var wire 32 Z WIDTH [31:0] $end
      $var wire 32 * a [31:0] $end
      $var wire 32 + b [31:0] $end
      $var wire 64 5 intermediate [63:0] $end
      $var wire 32 1 result [31:0] $end
     $upscope $end
     $scope module b_b $end
      $var wire 32 Z WIDTH [31:0] $end
      $var wire 32 + a [31:0] $end
      $var wire 32 + b [31:0] $end
      $var wire 64 7 intermediate [63:0] $end
      $var wire 32 0 result [31:0] $end
     $upscope $end
    $upscope $end
   $upscope $end
   $scope module Mapper $end
    $var wire 10 9 X [9:0] $end
    $var wire 32 T XtimesDelta [31:0] $end
    $var wire 10 # Y [9:0] $end
    $var wire 32 U YtimesDelta [31:0] $end
    $var wire  1 G clock $end
    $var wire 32 P delta_x [31:0] $end
    $var wire 32 Q delta_y [31:0] $end
    $var wire  1 S en $end
    $var wire 32 L im_axis_width [31:0] $end
    $var wire 32 R ims [31:0] $end
    $var wire  1 $ ovf $end
    $var wire 32 K re_axis_width [31:0] $end
    $var wire 32 ? real_s [31:0] $end
    $var wire  1 F rst $end
    $var wire 10 # x [9:0] $end
    $var wire 10 # y [9:0] $end
    $scope module DIMENSIONS $end
     $var wire  1 $ OVF $end
     $var wire 10 9 X [9:0] $end
     $var wire 10 # Y [9:0] $end
     $var wire  1 G clk $end
     $var wire  1 S en $end
     $var wire  1 F rst $end
    $upscope $end
    $scope module XtimesDELTA $end
     $var wire 32 Z WIDTH [31:0] $end
     $var wire 32 : a [31:0] $end
     $var wire 32 P b [31:0] $end
     $var wire 64 V intermediate [63:0] $end
     $var wire 32 T result [31:0] $end
    $upscope $end
    $scope module YtimesDELTA $end
     $var wire 32 Z WIDTH [31:0] $end
     $var wire 32 ; a [31:0] $end
     $var wire 32 Q b [31:0] $end
     $var wire 64 X intermediate [63:0] $end
     $var wire 32 U result [31:0] $end
    $upscope $end
   $upscope $end
   $scope module addr_counter $end
    $var wire 10 N X [9:0] $end
    $var wire 10 O Y [9:0] $end
    $var wire 20 ) addr_count [19:0] $end
    $var wire  1 G clk $end
    $var wire  1 $ en $end
    $var wire  1 F rst $end
   $upscope $end
   $scope module counter_mod $end
    $var wire  1 G clk $end
    $var wire 15 ' counter [14:0] $end
    $var wire 15 < counter_reg [14:0] $end
    $var wire  1 H en $end
    $var wire  1 ( ovf $end
    $var wire  1 @ rst $end
   $upscope $end
   $scope module ram $end
    $var wire 32 [ ADDRESS_WIDTH [31:0] $end
    $var wire 32 \ DATA_WIDTH [31:0] $end
    $var wire  1 $ READ_EN $end
    $var wire 15 M RGB [14:0] $end
    $var wire  1 = WRITE_EN $end
    $var wire  1 G clk $end
    $var wire 15 ' din [14:0] $end
    $var wire 20 ) rd_addr [19:0] $end
    $var wire 20 > wr_addr [19:0] $end
   $upscope $end
   $scope module top_f $end
    $var wire  1 G clk $end
    $var wire  1 % q $end
    $var wire  1 & q_bar $end
    $var wire  1 F reset $end
    $var wire  1 $ s $end
   $upscope $end
  $upscope $end
 $upscope $end
$enddefinitions $end


#0
b0000000000 #
0$
0%
0&
b000000000000000 '
0(
b00000000000000000000 )
b00000000000000000000000000000000 *
b00000000000000000000000000000000 +
b00000000000000000000000000000000 ,
b00000000000000000000000000000000 -
b00000000000000000000000000000000 .
b00000000000000000000000000000000 /
b00000000000000000000000000000000 0
b00000000000000000000000000000000 1
b0000000000000000000000000000000 2
b0000000000000000000000000000000000000000000000000000000000000000 3
b0000000000000000000000000000000000000000000000000000000000000000 5
b0000000000000000000000000000000000000000000000000000000000000000 7
b0000000000 9
b00000000000000000000000000000000 :
b00000000000000000000000000000000 ;
b000000000000000 <
1=
b00000000000000000000 >
b00000000000000000000000000000000 ?
0@
0A
b00000000000000000000000000000000 B
b00000000000000000000000000000000 C
b00000000000000000000000000000000 D
b00000000000000000000000000000000 E
1F
0G
1H
b0000000000 I
b0000000000 J
b11111111110100000000000000000000 K
b11111111110000000000000000000000 L
b000000000000000 M
b0000000000 N
b0000000000 O
b00000000000000000000000000000000 P
b00000000000000000000000000000000 Q
b11111111110000000000000000000000 R
0S
b00000000000000000000000000000000 T
b00000000000000000000000000000000 U
b0000000000000000000000000000000000000000000000000000000000000000 V
b0000000000000000000000000000000000000000000000000000000000000000 X
b00000000000000000000000000100000 Z
b00000000000000000000000000010100 [
b00000000000000000000000000001111 \
#1
b11111111110100000000000000000000 ?
1@
1A
b11111111110100000000000000000000 B
b11111111110000000000000000000000 C
1G
#2
0G
#3
1&
1G
1S
#4
0G
#5
1G
#6
0G
#7
1G
#8
0G
#9
1G
#10
0G
#11
1G
#12
0F
0G
#13
b0000000001 9
b00000000001000000000000000000000 :
1G
#14
0G
#15
b0000000010 9
b00000000010000000000000000000000 :
1G
#16
0G
#17
b0000000011 9
b00000000011000000000000000000000 :
1G
#18
0G
#19
b0000000100 9
b00000000100000000000000000000000 :
1G
#20
0G
#21
b0000000101 9
b00000000101000000000000000000000 :
1G
#22
0G
#23
b0000000110 9
b00000000110000000000000000000000 :
1G
#24
0G
#25
b0000000111 9
b00000000111000000000000000000000 :
1G
#26
0G
#27
b0000001000 9
b00000001000000000000000000000000 :
1G
#28
0G
#29
b0000001001 9
b00000001001000000000000000000000 :
1G
#30
0G
#31
b0000001010 9
b00000001010000000000000000000000 :
1G
#32
0G
#33
b0000001011 9
b00000001011000000000000000000000 :
1G
#34
0G
#35
b0000001100 9
b00000001100000000000000000000000 :
1G
#36
0G
#37
b0000001101 9
b00000001101000000000000000000000 :
1G
#38
0G
#39
b0000001110 9
b00000001110000000000000000000000 :
1G
#40
0G
#41
b0000001111 9
b00000001111000000000000000000000 :
1G
#42
0G
#43
b0000010000 9
b00000010000000000000000000000000 :
1G
#44
0G
#45
b0000010001 9
b00000010001000000000000000000000 :
1G
#46
0G
#47
b0000010010 9
b00000010010000000000000000000000 :
1G
#48
0G
#49
b0000010011 9
b00000010011000000000000000000000 :
1G
#50
0G
#51
b0000010100 9
b00000010100000000000000000000000 :
1G
#52
0G
#53
b0000010101 9
b00000010101000000000000000000000 :
1G
#54
0G
#55
b0000010110 9
b00000010110000000000000000000000 :
1G
#56
0G
#57
b0000010111 9
b00000010111000000000000000000000 :
1G
#58
0G
#59
b0000011000 9
b00000011000000000000000000000000 :
1G
#60
0G
#61
b0000011001 9
b00000011001000000000000000000000 :
1G
#62
0G
#63
b0000011010 9
b00000011010000000000000000000000 :
1G
#64
0G
#65
b0000011011 9
b00000011011000000000000000000000 :
1G
#66
0G
#67
b0000011100 9
b00000011100000000000000000000000 :
1G
#68
0G
#69
b0000011101 9
b00000011101000000000000000000000 :
1G
#70
0G
#71
b0000011110 9
b00000011110000000000000000000000 :
1G
#72
0G
#73
b0000011111 9
b00000011111000000000000000000000 :
1G
#74
0G
#75
b0000100000 9
b00000100000000000000000000000000 :
1G
#76
0G
#77
b0000100001 9
b00000100001000000000000000000000 :
1G
#78
0G
#79
b0000100010 9
b00000100010000000000000000000000 :
1G
#80
0G
#81
b0000100011 9
b00000100011000000000000000000000 :
1G
#82
0G
#83
b0000100100 9
b00000100100000000000000000000000 :
1G
#84
0G
#85
b0000100101 9
b00000100101000000000000000000000 :
1G
#86
0G
#87
b0000100110 9
b00000100110000000000000000000000 :
1G
#88
0G
#89
b0000100111 9
b00000100111000000000000000000000 :
1G
#90
0G
#91
b0000101000 9
b00000101000000000000000000000000 :
1G
#92
0G
#93
b0000101001 9
b00000101001000000000000000000000 :
1G
#94
0G
#95
b0000101010 9
b00000101010000000000000000000000 :
1G
#96
0G
#97
b0000101011 9
b00000101011000000000000000000000 :
1G
#98
0G
#99
b0000101100 9
b00000101100000000000000000000000 :
1G
#100
0G
#101
b0000101101 9
b00000101101000000000000000000000 :
1G
#102
0G
#103
b0000101110 9
b00000101110000000000000000000000 :
1G
#104
0G
#105
b0000101111 9
b00000101111000000000000000000000 :
1G
#106
0G
#107
b0000110000 9
b00000110000000000000000000000000 :
1G
#108
0G
#109
b0000110001 9
b00000110001000000000000000000000 :
1G
#110
0G
#111
b0000110010 9
b00000110010000000000000000000000 :
1G
#112
0G
#113
b0000110011 9
b00000110011000000000000000000000 :
1G
#114
0G
#115
b0000110100 9
b00000110100000000000000000000000 :
1G
#116
0G
#117
b0000110101 9
b00000110101000000000000000000000 :
1G
#118
0G
#119
b0000110110 9
b00000110110000000000000000000000 :
1G
#120
0G
#121
b0000110111 9
b00000110111000000000000000000000 :
1G
#122
0G
#123
b0000111000 9
b00000111000000000000000000000000 :
1G
#124
0G
#125
b0000111001 9
b00000111001000000000000000000000 :
1G
#126
0G
#127
b0000111010 9
b00000111010000000000000000000000 :
1G
#128
0G
#129
b0000111011 9
b00000111011000000000000000000000 :
1G
#130
0G
#131
b0000111100 9
b00000111100000000000000000000000 :
1G
#132
0G
#133
b0000111101 9
b00000111101000000000000000000000 :
1G
#134
0G
#135
b0000111110 9
b00000111110000000000000000000000 :
1G
#136
0G
#137
b0000111111 9
b00000111111000000000000000000000 :
1G
#138
0G
#139
b0001000000 9
b00001000000000000000000000000000 :
1G
#140
0G
#141
b0001000001 9
b00001000001000000000000000000000 :
1G
#142
0G
#143
b0001000010 9
b00001000010000000000000000000000 :
1G
#144
0G
#145
b0001000011 9
b00001000011000000000000000000000 :
1G
#146
0G
#147
b0001000100 9
b00001000100000000000000000000000 :
1G
#148
0G
#149
b0001000101 9
b00001000101000000000000000000000 :
1G
#150
0G
#151
b0001000110 9
b00001000110000000000000000000000 :
1G
#152
0G
#153
b0001000111 9
b00001000111000000000000000000000 :
1G
#154
0G
#155
b0001001000 9
b00001001000000000000000000000000 :
1G
#156
0G
#157
b0001001001 9
b00001001001000000000000000000000 :
1G
#158
0G
#159
b0001001010 9
b00001001010000000000000000000000 :
1G
#160
0G
#161
b0001001011 9
b00001001011000000000000000000000 :
1G
#162
0G
#163
b0001001100 9
b00001001100000000000000000000000 :
1G
#164
0G
#165
b0001001101 9
b00001001101000000000000000000000 :
1G
#166
0G
#167
b0001001110 9
b00001001110000000000000000000000 :
1G
#168
0G
#169
b0001001111 9
b00001001111000000000000000000000 :
1G
#170
0G
#171
b0001010000 9
b00001010000000000000000000000000 :
1G
#172
0G
#173
b0001010001 9
b00001010001000000000000000000000 :
1G
#174
0G
#175
b0001010010 9
b00001010010000000000000000000000 :
1G
#176
0G
#177
b0001010011 9
b00001010011000000000000000000000 :
1G
#178
0G
#179
b0001010100 9
b00001010100000000000000000000000 :
1G
#180
0G
#181
b0001010101 9
b00001010101000000000000000000000 :
1G
#182
0G
#183
b0001010110 9
b00001010110000000000000000000000 :
1G
#184
0G
#185
b0001010111 9
b00001010111000000000000000000000 :
1G
#186
0G
#187
b0001011000 9
b00001011000000000000000000000000 :
1G
#188
0G
#189
b0001011001 9
b00001011001000000000000000000000 :
1G
#190
0G
#191
b0001011010 9
b00001011010000000000000000000000 :
1G
#192
0G
#193
b0001011011 9
b00001011011000000000000000000000 :
1G
#194
0G
#195
b0001011100 9
b00001011100000000000000000000000 :
1G
#196
0G
#197
b0001011101 9
b00001011101000000000000000000000 :
1G
#198
0G
#199
b0001011110 9
b00001011110000000000000000000000 :
1G
#200
0G
#201
b0001011111 9
b00001011111000000000000000000000 :
1G
#202
0G
#203
b0001100000 9
b00001100000000000000000000000000 :
1G
#204
0G
#205
b0001100001 9
b00001100001000000000000000000000 :
1G
#206
0G
#207
b0001100010 9
b00001100010000000000000000000000 :
1G
#208
0G
#209
b0001100011 9
b00001100011000000000000000000000 :
1G
#210
0G
#211
b0001100100 9
b00001100100000000000000000000000 :
1G
#212
0G
#213
b0001100101 9
b00001100101000000000000000000000 :
1G
#214
0G
#215
b0001100110 9
b00001100110000000000000000000000 :
1G
#216
0G
#217
b0001100111 9
b00001100111000000000000000000000 :
1G
#218
0G
#219
b0001101000 9
b00001101000000000000000000000000 :
1G
#220
0G
#221
b0001101001 9
b00001101001000000000000000000000 :
1G
#222
0G
#223
b0001101010 9
b00001101010000000000000000000000 :
1G
#224
0G
#225
b0001101011 9
b00001101011000000000000000000000 :
1G
#226
0G
#227
b0001101100 9
b00001101100000000000000000000000 :
1G
#228
0G
#229
b0001101101 9
b00001101101000000000000000000000 :
1G
#230
0G
#231
b0001101110 9
b00001101110000000000000000000000 :
1G
#232
0G
#233
b0001101111 9
b00001101111000000000000000000000 :
1G
#234
0G
#235
b0001110000 9
b00001110000000000000000000000000 :
1G
#236
0G
#237
b0001110001 9
b00001110001000000000000000000000 :
1G
#238
0G
#239
b0001110010 9
b00001110010000000000000000000000 :
1G
#240
0G
#241
b0001110011 9
b00001110011000000000000000000000 :
1G
#242
0G
#243
b0001110100 9
b00001110100000000000000000000000 :
1G
#244
0G
#245
b0001110101 9
b00001110101000000000000000000000 :
1G
#246
0G
#247
b0001110110 9
b00001110110000000000000000000000 :
1G
#248
0G
#249
b0001110111 9
b00001110111000000000000000000000 :
1G
#250
0G
#251
b0001111000 9
b00001111000000000000000000000000 :
1G
#252
0G
#253
b0001111001 9
b00001111001000000000000000000000 :
1G
#254
0G
#255
b0001111010 9
b00001111010000000000000000000000 :
1G
#256
0G
#257
b0001111011 9
b00001111011000000000000000000000 :
1G
#258
0G
#259
b0001111100 9
b00001111100000000000000000000000 :
1G
#260
0G
#261
b0001111101 9
b00001111101000000000000000000000 :
1G
#262
0G
#263
b0001111110 9
b00001111110000000000000000000000 :
1G
#264
0G
#265
b0001111111 9
b00001111111000000000000000000000 :
1G
#266
0G
#267
b0010000000 9
b00010000000000000000000000000000 :
1G
#268
0G
#269
b0010000001 9
b00010000001000000000000000000000 :
1G
#270
0G
#271
b0010000010 9
b00010000010000000000000000000000 :
1G
#272
0G
#273
b0010000011 9
b00010000011000000000000000000000 :
1G
#274
0G
#275
b0010000100 9
b00010000100000000000000000000000 :
1G
#276
0G
#277
b0010000101 9
b00010000101000000000000000000000 :
1G
#278
0G
#279
b0010000110 9
b00010000110000000000000000000000 :
1G
#280
0G
#281
b0010000111 9
b00010000111000000000000000000000 :
1G
#282
0G
#283
b0010001000 9
b00010001000000000000000000000000 :
1G
#284
0G
#285
b0010001001 9
b00010001001000000000000000000000 :
1G
#286
0G
#287
b0010001010 9
b00010001010000000000000000000000 :
1G
#288
0G
#289
b0010001011 9
b00010001011000000000000000000000 :
1G
#290
0G
#291
b0010001100 9
b00010001100000000000000000000000 :
1G
#292
0G
#293
b0010001101 9
b00010001101000000000000000000000 :
1G
#294
0G
#295
b0010001110 9
b00010001110000000000000000000000 :
1G
#296
0G
#297
b0010001111 9
b00010001111000000000000000000000 :
1G
#298
0G
#299
b0010010000 9
b00010010000000000000000000000000 :
1G
#300
0G
#301
b0010010001 9
b00010010001000000000000000000000 :
1G
#302
0G
#303
b0010010010 9
b00010010010000000000000000000000 :
1G
#304
0G
#305
b0010010011 9
b00010010011000000000000000000000 :
1G
#306
0G
#307
b0010010100 9
b00010010100000000000000000000000 :
1G
#308
0G
#309
b0010010101 9
b00010010101000000000000000000000 :
1G
#310
0G
#311
b0010010110 9
b00010010110000000000000000000000 :
1G
#312
0G
#313
b0010010111 9
b00010010111000000000000000000000 :
1G
#314
0G
#315
b0010011000 9
b00010011000000000000000000000000 :
1G
#316
0G
#317
b0010011001 9
b00010011001000000000000000000000 :
1G
#318
0G
#319
b0010011010 9
b00010011010000000000000000000000 :
1G
#320
0G
#321
b0010011011 9
b00010011011000000000000000000000 :
1G
#322
0G
#323
b0010011100 9
b00010011100000000000000000000000 :
1G
#324
0G
#325
b0010011101 9
b00010011101000000000000000000000 :
1G
#326
0G
#327
b0010011110 9
b00010011110000000000000000000000 :
1G
#328
0G
#329
b0010011111 9
b00010011111000000000000000000000 :
1G
#330
0G
#331
b0010100000 9
b00010100000000000000000000000000 :
1G
#332
0G
#333
b0010100001 9
b00010100001000000000000000000000 :
1G
#334
0G
#335
b0010100010 9
b00010100010000000000000000000000 :
1G
#336
0G
#337
b0010100011 9
b00010100011000000000000000000000 :
1G
#338
0G
#339
b0010100100 9
b00010100100000000000000000000000 :
1G
#340
0G
#341
b0010100101 9
b00010100101000000000000000000000 :
1G
#342
0G
#343
b0010100110 9
b00010100110000000000000000000000 :
1G
#344
0G
#345
b0010100111 9
b00010100111000000000000000000000 :
1G
#346
0G
#347
b0010101000 9
b00010101000000000000000000000000 :
1G
#348
0G
#349
b0010101001 9
b00010101001000000000000000000000 :
1G
#350
0G
#351
b0010101010 9
b00010101010000000000000000000000 :
1G
#352
0G
#353
b0010101011 9
b00010101011000000000000000000000 :
1G
#354
0G
#355
b0010101100 9
b00010101100000000000000000000000 :
1G
#356
0G
#357
b0010101101 9
b00010101101000000000000000000000 :
1G
#358
0G
#359
b0010101110 9
b00010101110000000000000000000000 :
1G
#360
0G
#361
b0010101111 9
b00010101111000000000000000000000 :
1G
#362
0G
#363
b0010110000 9
b00010110000000000000000000000000 :
1G
#364
0G
#365
b0010110001 9
b00010110001000000000000000000000 :
1G
#366
0G
#367
b0010110010 9
b00010110010000000000000000000000 :
1G
#368
0G
#369
b0010110011 9
b00010110011000000000000000000000 :
1G
#370
0G
#371
b0010110100 9
b00010110100000000000000000000000 :
1G
#372
0G
#373
b0010110101 9
b00010110101000000000000000000000 :
1G
#374
0G
#375
b0010110110 9
b00010110110000000000000000000000 :
1G
#376
0G
#377
b0010110111 9
b00010110111000000000000000000000 :
1G
#378
0G
#379
b0010111000 9
b00010111000000000000000000000000 :
1G
#380
0G
#381
b0010111001 9
b00010111001000000000000000000000 :
1G
#382
0G
#383
b0010111010 9
b00010111010000000000000000000000 :
1G
#384
0G
#385
b0010111011 9
b00010111011000000000000000000000 :
1G
#386
0G
#387
b0010111100 9
b00010111100000000000000000000000 :
1G
#388
0G
#389
b0010111101 9
b00010111101000000000000000000000 :
1G
#390
0G
#391
b0010111110 9
b00010111110000000000000000000000 :
1G
#392
0G
#393
b0010111111 9
b00010111111000000000000000000000 :
1G
#394
0G
#395
b0011000000 9
b00011000000000000000000000000000 :
1G
#396
0G
#397
b0011000001 9
b00011000001000000000000000000000 :
1G
#398
0G
#399
b0011000010 9
b00011000010000000000000000000000 :
1G
#400
0G
#401
b0011000011 9
b00011000011000000000000000000000 :
1G
#402
0G
#403
b0011000100 9
b00011000100000000000000000000000 :
1G
#404
0G
#405
b0011000101 9
b00011000101000000000000000000000 :
1G
#406
0G
#407
b0011000110 9
b00011000110000000000000000000000 :
1G
#408
0G
#409
b0011000111 9
b00011000111000000000000000000000 :
1G
#410
0G
#411
b0011001000 9
b00011001000000000000000000000000 :
1G
#412
0G
#413
b0011001001 9
b00011001001000000000000000000000 :
1G
#414
0G
#415
b0011001010 9
b00011001010000000000000000000000 :
1G
#416
0G
#417
b0011001011 9
b00011001011000000000000000000000 :
1G
#418
0G
#419
b0011001100 9
b00011001100000000000000000000000 :
1G
#420
0G
#421
b0011001101 9
b00011001101000000000000000000000 :
1G
#422
0G
#423
b0011001110 9
b00011001110000000000000000000000 :
1G
#424
0G
#425
b0011001111 9
b00011001111000000000000000000000 :
1G
#426
0G
#427
b0011010000 9
b00011010000000000000000000000000 :
1G
#428
0G
#429
b0011010001 9
b00011010001000000000000000000000 :
1G
#430
0G
