rainbow_test/Ram.sv
module Ram #(
    parameter ADDRESS_WIDTH = 20,
            DATA_WIDTH = 15
)(
    input logic clk,
    input logic WRITE_EN,
    input logic READ_EN,
    input logic [ADDRESS_WIDTH-1:0] rd_addr,
    input logic [ADDRESS_WIDTH-1:0] wr_addr,
    input logic [DATA_WIDTH-1:0] din,
    output logic [DATA_WIDTH-1:0] RGB
);

logic [DATA_WIDTH-1:0] ram_array [2**ADDRESS_WIDTH-1:0];


always_ff @(posedge clk) begin
    if (WRITE_EN ==1'b1)
        ram_array[wr_addr] <=din;
    if (READ_EN == 1'b1)
        RGB <= ram_array[rd_addr];
end 

endmodule

rainbow_test/Addr_counter.sv
module Addr_counter(
    input logic clk, 
    input logic en, 
    input logic rst, 
    output logic [19:0] addr_count
);

always_ff @(posedge clk)
begin
    if (rst)
        addr_count <= 20'b0;
    else if (addr_count == 20'hFFFFF)
        addr_count <= 20'b0;
    else if (en)
        addr_count <= addr_count + 20'b01;
end

endmodule

rainbow test/pixel.sv
module Pixel (
    input logic clk, 
    input logic en, 
    input logic rst,
    output logic OVF,
    output logic [9:0] X,
    output logic [9:0] Y
);

always_ff @posedge (clk)
    if (rst) begin
        X <= 10'b0;
        Y <= 10'b0;
        OVF <= 1'b0;
    end 

    else if (X == 10'h3FF) begin 
        if (Y == 10'h2FF)
            OVF <= 1;
            Y <= 10'b0;
    end 

    else 
        X <= X + 10'b01

endmodule

Counter.sv
// Pointer moves through whole image from top left to bottom right in a rastern pattern and stops at each pixel
// and counts the number of iterations it takes for that specific 'pixel' to diverge. It diverges when the absolute
// value of Z_n is greater than 2. The pixels are assigned a color based on how quickly they diverge. It is assigned
// black if it is in the Mandelbrot set, and therefore never diverges, and red if it diverges. Any color between is purely
// for aesthetic appeal and represents how quickly that point diverges. A true Mandelbrot set is black and white.

module Counter (
    input logic clk,
    input logic rst,
    input logic en,
    output logic [14:0] Count
);

always_ff @(posedge clk)
    if (rst) 
        Count <= 15'b0;
    else if (en)
        Count <= Count + 15'b0100;


endmodule

rainbow_test/top_level.sv
module top_level(
    input  logic clk,
    input  logic enable,
    input  logic rst,
    output logic [14:0] RGB_out
);

logic [14:0] count_out;
Counter counter(
    .clk(clk),
    .rst(rst),
    .en(enable),
    .Count(count_out)
);

logic ovf;
logic [9:0] x;
logic [9:0] y;

Pixel pixel(
    .clk(clk), 
    .en(enable), 
    .rst(rst),
    .OVF(ovf),
    .X(x),
    .Y(y) 
);

logic [19:0] rd_addr;
Addr_counter addr_counter(
    .clk(clk),
    .rst(rst),
    .en(ovf),
    .addr_count(rd_addr)
);


Ram ram(
    .clk(clk),
    .WRITE_EN(~ovf),
    .READ_EN(ovf),
    .rd_addr(rd_addr),
    .wr_addr({y,x}),
    .din(count_out),
    .RGB(RGB_out)
);


endmodule

rainbow_test/rainbow.vcd
$version Generated by VerilatedVcd $end
$timescale 1ps $end

 $scope module TOP $end
  $var wire 15 - RGB_out [14:0] $end
  $var wire  1 * clk $end
  $var wire  1 + enable $end
  $var wire  1 , rst $end
  $scope module top_level $end
   $var wire 15 - RGB_out [14:0] $end
   $var wire  1 * clk $end
   $var wire 15 # count_out [14:0] $end
   $var wire  1 + enable $end
   $var wire  1 $ ovf $end
   $var wire 20 ' rd_addr [19:0] $end
   $var wire  1 , rst $end
   $var wire 10 % x [9:0] $end
   $var wire 10 & y [9:0] $end
   $scope module addr_counter $end
    $var wire 20 ' addr_count [19:0] $end
    $var wire  1 * clk $end
    $var wire  1 $ en $end
    $var wire  1 , rst $end
   $upscope $end
   $scope module counter $end
    $var wire 15 # Count [14:0] $end
    $var wire  1 * clk $end
    $var wire  1 + en $end
    $var wire  1 , rst $end
   $upscope $end
   $scope module pixel $end
    $var wire  1 $ OVF $end
    $var wire 10 % X [9:0] $end
    $var wire 10 & Y [9:0] $end
    $var wire  1 * clk $end
    $var wire  1 + en $end
    $var wire  1 , rst $end
   $upscope $end
   $scope module ram $end
    $var wire 32 . ADDRESS_WIDTH [31:0] $end
    $var wire 32 / DATA_WIDTH [31:0] $end
    $var wire  1 $ READ_EN $end
    $var wire 15 - RGB [14:0] $end
    $var wire  1 ( WRITE_EN $end
    $var wire  1 * clk $end
    $var wire 15 # din [14:0] $end
    $var wire 20 ' rd_addr [19:0] $end
    $var wire 20 ) wr_addr [19:0] $end
   $upscope $end
  $upscope $end
 $upscope $end
$enddefinitions $end


#0
b000000000000000 #
0$
b0000000000 %
b0000000000 &
b00000000000000000000 '
1(
b00000000000000000000 )
0*
1+
0,
b000000000000000 -
b00000000000000000000000000010100 .
b00000000000000000000000000001111 /
#1
1*
#2
0*
#3
b000000000000100 #
b0000000001 %
b00000000000000000001 )
1*
#4
0*
#5
b000000000001000 #
b0000000010 %
b00000000000000000010 )
1*
#6
0*
#7
b000000000001100 #
b0000000011 %
b00000000000000000011 )
1*
#8
0*
#9
b000000000010000 #
b0000000100 %
b00000000000000000100 )
1*
#10
0*
#11
b000000000010100 #
b0000000101 %
b00000000000000000101 )
1*
#12
0*
#13
b000000000011000 #
b0000000110 %
b00000000000000000110 )
1*
#14
0*
#15
b000000000011100 #
b0000000111 %
b00000000000000000111 )
1*
#16
0*
#17
b000000000100000 #
b0000001000 %
b00000000000000001000 )
1*
#18
0*
#19
b000000000100100 #
b0000001001 %
b00000000000000001001 )
1*
#20
0*
#21
b000000000101000 #
b0000001010 %
b00000000000000001010 )
1*
#22
0*
#23
b000000000101100 #
b0000001011 %
b00000000000000001011 )
1*
#24
0*
#25
b000000000110000 #
b0000001100 %
b00000000000000001100 )
1*
#26
0*
#27
b000000000110100 #
b0000001101 %
b00000000000000001101 )
1*
#28
0*
#29
b000000000111000 #
b0000001110 %
b00000000000000001110 )
1*
#30
0*
#31
b000000000111100 #
b0000001111 %
b00000000000000001111 )
1*
#32
0*
#33
b000000001000000 #
b0000010000 %
b00000000000000010000 )
1*
#34
0*
#35
b000000001000100 #
b0000010001 %
b00000000000000010001 )
1*
#36
0*
#37
b000000001001000 #
b0000010010 %
b00000000000000010010 )
1*
#38
0*
#39
b000000001001100 #
b0000010011 %
b00000000000000010011 )
1*
#40
0*
#41
b000000001010000 #
b0000010100 %
b00000000000000010100 )
1*
#42
0*
#43
b000000001010100 #
b0000010101 %
b00000000000000010101 )
1*
#44
0*
#45
b000000001011000 #
b0000010110 %
b00000000000000010110 )
1*
#46
0*
#47
b000000001011100 #
b0000010111 %
b00000000000000010111 )
1*
#48
0*
#49
b000000001100000 #
b0000011000 %
b00000000000000011000 )
1*
#50
0*
#51
b000000001100100 #
b0000011001 %
b00000000000000011001 )
1*
#52
0*
#53
b000000001101000 #
b0000011010 %
b00000000000000011010 )
1*
#54
0*
#55
b000000001101100 #
b0000011011 %
b00000000000000011011 )
1*
#56
0*
#57
b000000001110000 #
b0000011100 %
b00000000000000011100 )
1*
#58
0*
#59
b000000001110100 #
b0000011101 %
b00000000000000011101 )
1*
#60
0*
#61
b000000001111000 #
b0000011110 %
b00000000000000011110 )
1*
#62
0*
#63
b000000001111100 #
b0000011111 %
b00000000000000011111 )
1*
#64
0*
#65
b000000010000000 #
b0000100000 %
b00000000000000100000 )
1*
#66
0*
#67
b000000010000100 #
b0000100001 %
b00000000000000100001 )
1*
#68
0*
#69
b000000010001000 #
b0000100010 %
b00000000000000100010 )
1*
#70
0*
#71
b000000010001100 #
b0000100011 %
b00000000000000100011 )
1*
#72
0*
#73
b000000010010000 #
b0000100100 %
b00000000000000100100 )
1*
#74
0*
#75
b000000010010100 #
b0000100101 %
b00000000000000100101 )
1*
#76
0*
#77
b000000010011000 #
b0000100110 %
b00000000000000100110 )
1*
#78
0*
#79
b000000010011100 #
b0000100111 %
b00000000000000100111 )
1*
#80
0*
#81
b000000010100000 #
b0000101000 %
b00000000000000101000 )
1*
#82
0*
#83
b000000010100100 #
b0000101001 %
b00000000000000101001 )
1*
#84
0*
#85
b000000010101000 #
b0000101010 %
b00000000000000101010 )
1*
#86
0*
#87
b000000010101100 #
b0000101011 %
b00000000000000101011 )
1*
#88
0*
#89
b000000010110000 #
b0000101100 %
b00000000000000101100 )
1*
#90
0*
#91
b000000010110100 #
b0000101101 %
b00000000000000101101 )
1*
#92
0*
#93
b000000010111000 #
b0000101110 %
b00000000000000101110 )
1*
#94
0*
#95
b000000010111100 #
b0000101111 %
b00000000000000101111 )
1*
#96
0*
#97
b000000011000000 #
b0000110000 %
b00000000000000110000 )
1*
#98
0*
#99
b000000011000100 #
b0000110001 %
b00000000000000110001 )
1*
#100
0*
#101
b000000011001000 #
b0000110010 %
b00000000000000110010 )
1*
#102
0*
#103
b000000011001100 #
b0000110011 %
b00000000000000110011 )
1*
#104
0*
#105
b000000011010000 #
b0000110100 %
b00000000000000110100 )
1*
#106
0*
#107
b000000011010100 #
b0000110101 %
b00000000000000110101 )
1*
#108
0*
#109
b000000011011000 #
b0000110110 %
b00000000000000110110 )
1*
#110
0*
#111
b000000011011100 #
b0000110111 %
b00000000000000110111 )
1*
#112
0*
#113
b000000011100000 #
b0000111000 %
b00000000000000111000 )
1*
#114
0*
#115
b000000011100100 #
b0000111001 %
b00000000000000111001 )
1*
#116
0*
#117
b000000011101000 #
b0000111010 %
b00000000000000111010 )
1*
#118
0*
#119
b000000011101100 #
b0000111011 %
b00000000000000111011 )
1*
#120
0*
#121
b000000011110000 #
b0000111100 %
b00000000000000111100 )
1*
#122
0*
#123
b000000011110100 #
b0000111101 %
b00000000000000111101 )
1*
#124
0*
#125
b000000011111000 #
b0000111110 %
b00000000000000111110 )
1*
#126
0*
#127
b000000011111100 #
b0000111111 %
b00000000000000111111 )
1*
#128
0*
#129
b000000100000000 #
b0001000000 %
b00000000000001000000 )
1*
#130
0*
#131
b000000100000100 #
b0001000001 %
b00000000000001000001 )
1*
#132
0*
#133
b000000100001000 #
b0001000010 %
b00000000000001000010 )
1*
#134
0*
#135
b000000100001100 #
b0001000011 %
b00000000000001000011 )
1*
#136
0*
#137
b000000100010000 #
b0001000100 %
b00000000000001000100 )
1*
#138
0*
#139
b000000100010100 #
b0001000101 %
b00000000000001000101 )
1*
#140
0*
#141
b000000100011000 #
b0001000110 %
b00000000000001000110 )
1*
#142
0*
#143
b000000100011100 #
b0001000111 %
b00000000000001000111 )
1*
#144
0*
#145
b000000100100000 #
b0001001000 %
b00000000000001001000 )
1*
#146
0*
#147
b000000100100100 #
b0001001001 %
b00000000000001001001 )
1*
#148
0*
#149
b000000100101000 #
b0001001010 %
b00000000000001001010 )
1*
#150
0*
#151
b000000100101100 #
b0001001011 %
b00000000000001001011 )
1*
#152
0*
#153
b000000100110000 #
b0001001100 %
b00000000000001001100 )
1*
#154
0*
#155
b000000100110100 #
b0001001101 %
b00000000000001001101 )
1*
#156
0*
#157
b000000100111000 #
b0001001110 %
b00000000000001001110 )
1*
#158
0*
#159
b000000100111100 #
b0001001111 %
b00000000000001001111 )
1*
#160
0*
#161
b000000101000000 #
b0001010000 %
b00000000000001010000 )
1*
#162
0*
#163
b000000101000100 #
b0001010001 %
b00000000000001010001 )
1*
#164
0*
#165
b000000101001000 #
b0001010010 %
b00000000000001010010 )
1*
#166
0*
#167
b000000101001100 #
b0001010011 %
b00000000000001010011 )
1*
#168
0*
#169
b000000101010000 #
b0001010100 %
b00000000000001010100 )
1*
#170
0*
#171
b000000101010100 #
b0001010101 %
b00000000000001010101 )
1*
#172
0*
#173
b000000101011000 #
b0001010110 %
b00000000000001010110 )
1*
#174
0*
#175
b000000101011100 #
b0001010111 %
b00000000000001010111 )
1*
#176
0*
#177
b000000101100000 #
b0001011000 %
b00000000000001011000 )
1*
#178
0*
#179
b000000101100100 #
b0001011001 %
b00000000000001011001 )
1*
#180
0*
#181
b000000101101000 #
b0001011010 %
b00000000000001011010 )
1*
#182
0*
#183
b000000101101100 #
b0001011011 %
b00000000000001011011 )
1*
#184
0*
#185
b000000101110000 #
b0001011100 %
b00000000000001011100 )
1*
#186
0*
#187
b000000101110100 #
b0001011101 %
b00000000000001011101 )
1*
#188
0*
#189
b000000101111000 #
b0001011110 %
b00000000000001011110 )
1*
#190
0*
#191
b000000101111100 #
b0001011111 %
b00000000000001011111 )
1*
#192
0*
#193
b000000110000000 #
b0001100000 %
b00000000000001100000 )
1*
#194
0*
#195
b000000110000100 #
b0001100001 %
b00000000000001100001 )
1*
#196
0*
#197
b000000110001000 #
b0001100010 %
b00000000000001100010 )
1*
#198
0*
#199
b000000110001100 #
b0001100011 %
b00000000000001100011 )
1*
#200
0*
#201
b000000110010000 #
b0001100100 %
b00000000000001100100 )
1*
#202
0*
#203
b000000110010100 #
b0001100101 %
b00000000000001100101 )
1*
#204
0*
#205
b000000110011000 #
b0001100110 %
b00000000000001100110 )
1*
#206
0*
#207
b000000110011100 #
b0001100111 %
b00000000000001100111 )
1*
#208
0*
#209
b000000110100000 #
b0001101000 %
b00000000000001101000 )
1*
#210
0*
#211
b000000110100100 #
b0001101001 %
b00000000000001101001 )
1*
#212
0*
#213
b000000110101000 #
b0001101010 %
b00000000000001101010 )
1*
#214
0*
#215
b000000110101100 #
b0001101011 %
b00000000000001101011 )
1*
#216
0*
#217
b000000110110000 #
b0001101100 %
b00000000000001101100 )
1*
#218
0*
#219
b000000110110100 #
b0001101101 %
b00000000000001101101 )
1*
#220
0*
#221
b000000110111000 #
b0001101110 %
b00000000000001101110 )
1*
#222
0*
#223
b000000110111100 #
b0001101111 %
b00000000000001101111 )
1*
#224
0*
#225
b000000111000000 #
b0001110000 %
b00000000000001110000 )
1*
#226
0*
#227
b000000111000100 #
b0001110001 %
b00000000000001110001 )
1*
#228
0*
#229
b000000111001000 #
b0001110010 %
b00000000000001110010 )
1*
#230
0*
#231
b000000111001100 #
b0001110011 %
b00000000000001110011 )
1*
#232
0*
#233
b000000111010000 #
b0001110100 %
b00000000000001110100 )
1*
#234
0*
#235
b000000111010100 #
b0001110101 %
b00000000000001110101 )
1*
#236
0*
#237
b000000111011000 #
b0001110110 %
b00000000000001110110 )
1*
#238
0*
#239
b000000111011100 #
b0001110111 %
b00000000000001110111 )
1*
#240
0*
#241
b000000111100000 #
b0001111000 %
b00000000000001111000 )
1*
#242
0*
#243
b000000111100100 #
b0001111001 %
b00000000000001111001 )
1*
#244
0*
#245
b000000111101000 #
b0001111010 %
b00000000000001111010 )
1*
#246
0*
#247
b000000111101100 #
b0001111011 %
b00000000000001111011 )
1*
#248
0*
#249
b000000111110000 #
b0001111100 %
b00000000000001111100 )
1*
#250
0*
#251
b000000111110100 #
b0001111101 %
b00000000000001111101 )
1*
#252
0*
#253
b000000111111000 #
b0001111110 %
b00000000000001111110 )
1*
#254
0*
#255
b000000111111100 #
b0001111111 %
b00000000000001111111 )
1*
#256
0*
#257
b000001000000000 #
b0010000000 %
b00000000000010000000 )
1*
#258
0*
#259
b000001000000100 #
b0010000001 %
b00000000000010000001 )
1*
#260
0*
#261
b000001000001000 #
b0010000010 %
b00000000000010000010 )
1*
#262
0*
#263
b000001000001100 #
b0010000011 %
b00000000000010000011 )
1*
#264
0*
#265
b000001000010000 #
b0010000100 %
b00000000000010000100 )
1*
#266
0*
#267
b000001000010100 #
b0010000101 %
b00000000000010000101 )
1*
#268
0*
#269
b000001000011000 #
b0010000110 %
b00000000000010000110 )
1*
#270
0*
#271
b000001000011100 #
b0010000111 %
b00000000000010000111 )
1*
#272
0*
#273
b000001000100000 #
b0010001000 %
b00000000000010001000 )
1*
#274
0*
#275
b000001000100100 #
b0010001001 %
b00000000000010001001 )
1*
#276
0*
#277
b000001000101000 #
b0010001010 %
b00000000000010001010 )
1*
#278
0*
#279
b000001000101100 #
b0010001011 %
b00000000000010001011 )
1*
#280
0*
#281
b000001000110000 #
b0010001100 %
b00000000000010001100 )
1*
#282
0*
#283
b000001000110100 #
b0010001101 %
b00000000000010001101 )
1*
#284
0*
#285
b000001000111000 #
b0010001110 %
b00000000000010001110 )
1*
#286
0*
#287
b000001000111100 #
b0010001111 %
b00000000000010001111 )
1*
#288
0*
#289
b000001001000000 #
b0010010000 %
b00000000000010010000 )
1*
#290
0*
#291
b000001001000100 #
b0010010001 %
b00000000000010010001 )
1*
#292
0*
#293
b000001001001000 #
b0010010010 %
b00000000000010010010 )
1*
#294
0*
#295
b000001001001100 #
b0010010011 %
b00000000000010010011 )
1*
#296
0*
#297
b000001001010000 #
b0010010100 %
b00000000000010010100 )
1*
#298
0*
#299
b000001001010100 #
b0010010101 %
b00000000000010010101 )
1*
#300
0*
#301
b000001001011000 #
b0010010110 %
b00000000000010010110 )
1*
#302
0*
#303
b000001001011100 #
b0010010111 %
b00000000000010010111 )
1*
#304
0*
#305
b000001001100000 #
b0010011000 %
b00000000000010011000 )
1*
#306
0*
#307
b000001001100100 #
b0010011001 %
b00000000000010011001 )
1*
#308
0*
#309
b000001001101000 #
b0010011010 %
b00000000000010011010 )
1*
#310
0*
#311
b000001001101100 #
b0010011011 %
b00000000000010011011 )
1*
#312
0*
#313
b000001001110000 #
b0010011100 %
b00000000000010011100 )
1*
#314
0*
#315
b000001001110100 #
b0010011101 %
b00000000000010011101 )
1*
#316
0*
#317
b000001001111000 #
b0010011110 %
b00000000000010011110 )
1*
#318
0*
#319
b000001001111100 #
b0010011111 %
b00000000000010011111 )
1*
#320
0*
#321
b000001010000000 #
b0010100000 %
b00000000000010100000 )
1*
#322
0*
#323
b000001010000100 #
b0010100001 %
b00000000000010100001 )
1*
#324
0*
#325
b000001010001000 #
b0010100010 %
b00000000000010100010 )
1*
#326
0*
#327
b000001010001100 #
b0010100011 %
b00000000000010100011 )
1*
#328
0*
#329
b000001010010000 #
b0010100100 %
b00000000000010100100 )
1*
#330
0*
#331
b000001010010100 #
b0010100101 %
b00000000000010100101 )
1*
#332
0*
#333
b000001010011000 #
b0010100110 %
b00000000000010100110 )
1*
#334
0*
#335
b000001010011100 #
b0010100111 %
b00000000000010100111 )
1*
#336
0*
#337
b000001010100000 #
b0010101000 %
b00000000000010101000 )
1*
#338
0*
#339
b000001010100100 #
b0010101001 %
b00000000000010101001 )
1*
#340
0*
#341
b000001010101000 #
b0010101010 %
b00000000000010101010 )
1*
#342
0*
#343
b000001010101100 #
b0010101011 %
b00000000000010101011 )
1*
#344
0*
#345
b000001010110000 #
b0010101100 %
b00000000000010101100 )
1*
#346
0*
#347
b000001010110100 #
b0010101101 %
b00000000000010101101 )
1*
#348
0*
#349
b000001010111000 #
b0010101110 %
b00000000000010101110 )
1*
#350
0*
#351
b000001010111100 #
b0010101111 %
b00000000000010101111 )
1*
#352
0*
#353
b000001011000000 #
b0010110000 %
b00000000000010110000 )
1*
#354
0*
#355
b000001011000100 #
b0010110001 %
b00000000000010110001 )
1*
#356
0*
#357
b000001011001000 #
b0010110010 %
b00000000000010110010 )
1*
#358
0*
#359
b000001011001100 #
b0010110011 %
b00000000000010110011 )
1*
#360
0*
#361
b000001011010000 #
b0010110100 %
b00000000000010110100 )
1*
#362
0*
#363
b000001011010100 #
b0010110101 %
b00000000000010110101 )
1*
#364
0*
#365
b000001011011000 #
b0010110110 %
b00000000000010110110 )
1*
#366
0*
#367
b000001011011100 #
b0010110111 %
b00000000000010110111 )
1*
#368
0*
#369
b000001011100000 #
b0010111000 %
b00000000000010111000 )
1*
#370
0*
#371
b000001011100100 #
b0010111001 %
b00000000000010111001 )
1*
#372
0*
#373
b000001011101000 #
b0010111010 %
b00000000000010111010 )
1*
#374
0*
#375
b000001011101100 #
b0010111011 %
b00000000000010111011 )
1*
#376
0*
#377
b000001011110000 #
b0010111100 %
b00000000000010111100 )
1*
#378
0*
#379
b000001011110100 #
b0010111101 %
b00000000000010111101 )
1*
#380
0*
#381
b000001011111000 #
b0010111110 %
b00000000000010111110 )
1*
#382
0*
#383
b000001011111100 #
b0010111111 %
b00000000000010111111 )
1*
#384
0*
#385
b000001100000000 #
b0011000000 %
b00000000000011000000 )
1*
#386
0*
#387
b000001100000100 #
b0011000001 %
b00000000000011000001 )
1*
#388
0*
#389
b000001100001000 #
b0011000010 %
b00000000000011000010 )
1*
#390
0*
#391
b000001100001100 #
b0011000011 %
b00000000000011000011 )
1*
#392
0*
#393
b000001100010000 #
b0011000100 %
b00000000000011000100 )
1*
#394
0*
#395
b000001100010100 #
b0011000101 %
b00000000000011000101 )
1*
#396
0*
#397
b000001100011000 #
b0011000110 %
b00000000000011000110 )
1*
#398
0*
#399
b000001100011100 #
b0011000111 %
b00000000000011000111 )
1*
#400
0*
#401
b000001100100000 #
b0011001000 %
b00000000000011001000 )
1*
#402
0*
#403
b000001100100100 #
b0011001001 %
b00000000000011001001 )
1*
#404
0*
#405
b000001100101000 #
b0011001010 %
b00000000000011001010 )
1*
#406
0*
#407
b000001100101100 #
b0011001011 %
b00000000000011001011 )
1*
#408
0*
#409
b000001100110000 #
b0011001100 %
b00000000000011001100 )
1*
#410
0*
#411
b000001100110100 #
b0011001101 %
b00000000000011001101 )
1*
#412
0*
#413
b000001100111000 #
b0011001110 %
b00000000000011001110 )
1*
#414
0*
#415
b000001100111100 #
b0011001111 %
b00000000000011001111 )
1*
#416
0*
#417
b000001101000000 #
b0011010000 %
b00000000000011010000 )
1*
#418
0*
#419
b000001101000100 #
b0011010001 %
b00000000000011010001 )
1*
#420
0*
#421
b000001101001000 #
b0011010010 %
b00000000000011010010 )
1*
#422
0*
#423
b000001101001100 #
b0011010011 %
b00000000000011010011 )
1*
#424
0*
#425
b000001101010000 #
b0011010100 %
b00000000000011010100 )
1*
#426
0*
#427
b000001101010100 #
b0011010101 %
b00000000000011010101 )
1*
#428
0*
#429
b000001101011000 #
b0011010110 %
b00000000000011010110 )
1*
#430
0*
#431
b000001101011100 #
b0011010111 %
b00000000000011010111 )
1*
#432
0*
#433
b000001101100000 #
b0011011000 %
b00000000000011011000 )
1*
#434
0*
#435
b000001101100100 #
b0011011001 %
b00000000000011011001 )
1*
#436
0*
#437
b000001101101000 #
b0011011010 %
b00000000000011011010 )
1*
#438
0*
#439
b000001101101100 #
b0011011011 %
b00000000000011011011 )
1*
#440
0*
#441
b000001101110000 #
b0011011100 %
b00000000000011011100 )
1*
#442
0*
#443
b000001101110100 #
b0011011101 %
b00000000000011011101 )
1*
#444
0*
#445
b000001101111000 #
b0011011110 %
b00000000000011011110 )
1*
#446
0*
#447
b000001101111100 #
b0011011111 %
b00000000000011011111 )
1*
#448
0*
#449
b000001110000000 #
b0011100000 %
b00000000000011100000 )
1*
#450
0*
#451
b000001110000100 #
b0011100001 %
b00000000000011100001 )
1*
#452
0*
#453
b000001110001000 #
b0011100010 %
b00000000000011100010 )
1*
#454
0*
#455
b000001110001100 #
b0011100011 %
b00000000000011100011 )
1*
#456
0*
#457
b000001110010000 #
b0011100100 %
b00000000000011100100 )
1*
#458
0*
#459
b000001110010100 #
b0011100101 %
b00000000000011100101 )
1*
#460
0*
#461
b000001110011000 #
b0011100110 %
b00000000000011100110 )
1*
#462
0*
#463
b000001110011100 #
b0011100111 %
b00000000000011100111 )
1*
#464
0*
#465
b000001110100000 #
b0011101000 %
b00000000000011101000 )
1*
#466
0*
#467
b000001110100100 #
b0011101001 %
b00000000000011101001 )
1*
#468
0*
#469
b000001110101000 #
b0011101010 %
b00000000000011101010 )
1*
#470
0*
#471
b000001110101100 #
b0011101011 %
b00000000000011101011 )
1*
#472
0*
#473
b000001110110000 #
b0011101100 %
b00000000000011101100 )
1*
#474
0*
#475
b000001110110100 #
b0011101101 %
b00000000000011101101 )
1*
#476
0*
#477
b000001110111000 #
b0011101110 %
b00000000000011101110 )
1*
#478
0*
#479
b000001110111100 #
b0011101111 %
b00000000000011101111 )
1*
#480
0*
#481
b000001111000000 #
b0011110000 %
b00000000000011110000 )
1*
#482
0*
#483
b000001111000100 #
b0011110001 %
b00000000000011110001 )
1*
#484
0*
#485
b000001111001000 #
b0011110010 %
b00000000000011110010 )
1*
#486
0*
#487
b000001111001100 #
b0011110011 %
b00000000000011110011 )
1*
#488
0*
#489
b000001111010000 #
b0011110100 %
b00000000000011110100 )
1*
#490
0*
#491
b000001111010100 #
b0011110101 %
b00000000000011110101 )
1*
#492
0*
#493
b000001111011000 #
b0011110110 %
b00000000000011110110 )
1*
#494
0*
#495
b000001111011100 #
b0011110111 %
b00000000000011110111 )
1*
#496
0*
#497
b000001111100000 #
b0011111000 %
b00000000000011111000 )
1*
#498
0*
#499
b000001111100100 #
b0011111001 %
b00000000000011111001 )
1*
#500
0*
#501
b000001111101000 #
b0011111010 %
b00000000000011111010 )
1*
#502
0*
#503
b000001111101100 #
b0011111011 %
b00000000000011111011 )
1*
#504
0*
#505
b000001111110000 #
b0011111100 %
b00000000000011111100 )
1*
#506
0*
#507
b000001111110100 #
b0011111101 %
b00000000000011111101 )
1*
#508
0*
#509
b000001111111000 #
b0011111110 %
b00000000000011111110 )
1*
#510
0*
#511
b000001111111100 #
b0011111111 %
b00000000000011111111 )
1*
#512
0*
#513
b000010000000000 #
b0100000000 %
b00000000000100000000 )
1*
#514
0*
#515
b000010000000100 #
b0100000001 %
b00000000000100000001 )
1*
#516
0*
#517
b000010000001000 #
b0100000010 %
b00000000000100000010 )
1*
#518
0*
#519
b000010000001100 #
b0100000011 %
b00000000000100000011 )
1*
#520
0*
#521
b000010000010000 #
b0100000100 %
b00000000000100000100 )
1*
#522
0*
#523
b000010000010100 #
b0100000101 %
b00000000000100000101 )
1*
#524
0*
#525
b000010000011000 #
b0100000110 %
b00000000000100000110 )
1*
#526
0*
#527
b000010000011100 #
b0100000111 %
b00000000000100000111 )
1*
#528
0*
#529
b000010000100000 #
b0100001000 %
b00000000000100001000 )
1*
#530
0*
#531
b000010000100100 #
b0100001001 %
b00000000000100001001 )
1*
#532
0*
#533
b000010000101000 #
b0100001010 %
b00000000000100001010 )
1*
#534
0*
#535
b000010000101100 #
b0100001011 %
b00000000000100001011 )
1*
#536
0*
#537
b000010000110000 #
b0100001100 %
b00000000000100001100 )
1*
#538
0*
#539
b000010000110100 #
b0100001101 %
b00000000000100001101 )
1*
#540
0*
#541
b000010000111000 #
b0100001110 %
b00000000000100001110 )
1*
#542
0*
#543
b000010000111100 #
b0100001111 %
b00000000000100001111 )
1*
#544
0*
#545
b000010001000000 #
b0100010000 %
b00000000000100010000 )
1*
#546
0*
#547
b000010001000100 #
b0100010001 %
b00000000000100010001 )
1*
#548
0*
#549
b000010001001000 #
b0100010010 %
b00000000000100010010 )
1*
#550
0*
#551
b000010001001100 #
b0100010011 %
b00000000000100010011 )
1*
#552
0*
#553
b000010001010000 #
b0100010100 %
b00000000000100010100 )
1*
#554
0*
#555
b000010001010100 #
b0100010101 %
b00000000000100010101 )
1*
#556
0*
#557
b000010001011000 #
b0100010110 %
b00000000000100010110 )
1*
#558
0*
#559
b000010001011100 #
b0100010111 %
b00000000000100010111 )
1*
#560
0*
#561
b000010001100000 #
b0100011000 %
b00000000000100011000 )
1*
#562
0*
#563
b000010001100100 #
b0100011001 %
b00000000000100011001 )
1*
#564
0*
#565
b000010001101000 #
b0100011010 %
b00000000000100011010 )
1*
#566
0*
#567
b000010001101100 #
b0100011011 %
b00000000000100011011 )
1*
#568
0*
#569
b000010001110000 #
b0100011100 %
b00000000000100011100 )
1*
#570
0*
#571
b000010001110100 #
b0100011101 %
b00000000000100011101 )
1*
#572
0*
#573
b000010001111000 #
b0100011110 %
b00000000000100011110 )
1*
#574
0*
#575
b000010001111100 #
b0100011111 %
b00000000000100011111 )
1*
#576
0*
#577
b000010010000000 #
b0100100000 %
b00000000000100100000 )
1*
#578
0*
#579
b000010010000100 #
b0100100001 %
b00000000000100100001 )
1*
#580
0*
#581
b000010010001000 #
b0100100010 %
b00000000000100100010 )
1*
#582
0*
#583
b000010010001100 #
b0100100011 %
b00000000000100100011 )
1*
#584
0*
#585
b000010010010000 #
b0100100100 %
b00000000000100100100 )
1*
#586
0*
#587
b000010010010100 #
b0100100101 %
b00000000000100100101 )
1*
#588
0*
#589
b000010010011000 #
b0100100110 %
b00000000000100100110 )
1*
#590
0*
#591
b000010010011100 #
b0100100111 %
b00000000000100100111 )
1*
#592
0*
#593
b000010010100000 #
b0100101000 %
b00000000000100101000 )
1*
#594
0*
#595
b000010010100100 #
b0100101001 %
b00000000000100101001 )
1*
#596
0*
#597
b000010010101000 #
b0100101010 %
b00000000000100101010 )
1*
#598
0*
#599
b000010010101100 #
b0100101011 %
b00000000000100101011 )
1*
#600
0*
#601
b000010010110000 #
b0100101100 %
b00000000000100101100 )
1*
#602
0*
#603
b000010010110100 #
b0100101101 %
b00000000000100101101 )
1*
#604
0*
#605
b000010010111000 #
b0100101110 %
b00000000000100101110 )
1*
#606
0*
#607
b000010010111100 #
b0100101111 %
b00000000000100101111 )
1*
#608
0*
#609
b000010011000000 #
b0100110000 %
b00000000000100110000 )
1*
#610
0*
#611
b000010011000100 #
b0100110001 %
b00000000000100110001 )
1*
#612
0*
#613
b000010011001000 #
b0100110010 %
b00000000000100110010 )
1*
#614
0*
#615
b000010011001100 #
b0100110011 %
b00000000000100110011 )
1*
#616
0*
#617
b000010011010000 #
b0100110100 %
b00000000000100110100 )
1*
#618
0*
#619
b000010011010100 #
b0100110101 %
b00000000000100110101 )
1*
#620
0*
#621
b000010011011000 #
b0100110110 %
b00000000000100110110 )
1*
#622
0*
#623
b000010011011100 #
b0100110111 %
b00000000000100110111 )
1*
#624
0*
#625
b000010011100000 #
b0100111000 %
b00000000000100111000 )
1*
#626
0*
#627
b000010011100100 #
b0100111001 %
b00000000000100111001 )
1*
#628
0*
#629
b000010011101000 #
b0100111010 %
b00000000000100111010 )
1*
#630
0*
#631
b000010011101100 #
b0100111011 %
b00000000000100111011 )
1*
#632
0*
#633
b000010011110000 #
b0100111100 %
b00000000000100111100 )
1*
#634
0*
